fusionMCP.py
scriptsWebScrapping/extract_device_info.py
scriptsWebScrapping/extract_sessions.py
scriptsWebScrapping/extract_syslog.py
scriptsWebScrapping/extract_warnings.py
evchargers_mcp-0.2.4.dist-info/METADATA
evchargers_mcp-0.2.4.dist-info/WHEEL
evchargers_mcp-0.2.4.dist-info/entry_points.txt
evchargers_mcp-0.2.4.dist-info/top_level.txt
evchargers_mcp-0.2.4.dist-info/RECORD
